setup.py
test_PyPI_vincent/__init__.py
test_PyPI_vincent.egg-info/PKG-INFO
test_PyPI_vincent.egg-info/SOURCES.txt
test_PyPI_vincent.egg-info/dependency_links.txt
test_PyPI_vincent.egg-info/entry_points.txt
test_PyPI_vincent.egg-info/top_level.txt