Metadata-Version: 1.0
Name: test-PyPI-vincent
Version: 0.0.1
Summary: 吃枣药丸
Home-page: https://zhuanlan.zhihu.com/p/26159930
Author: vincent
Author-email: szxwpp@163.com
License: UNKNOWN
Platform: UNKNOWN
